{
    "created_time": "2021-12-21T06:40:35Z",
    "files": [
        {
            "attachment_folder": "",
            "created_time": "2021-12-21T06:40:51Z",
            "id": "19",
            "modified_time": "2021-12-27T10:19:35Z",
            "name": "车队定时任务整理.md",
            "signature": "27205962921715",
            "tags": [
            ]
        },
        {
            "attachment_folder": "",
            "created_time": "2021-12-22T01:25:39Z",
            "id": "20",
            "modified_time": "2021-12-23T06:15:45Z",
            "name": "v2.9-运营分析报告详细设计.md",
            "signature": "177733795475",
            "tags": [
            ]
        }
    ],
    "folders": [
    ],
    "id": "17",
    "modified_time": "2021-12-21T06:40:35Z",
    "signature": "177733727971",
    "version": 3
}
